<?xml version="1.0" encoding="UTF-8"?>
<TextureAtlas imagePath="sprites.png">
	<!--
	Created with ShoeBox
	http://renderhjs.net/shoebox/
	-->
	<SubTexture name="FishAvatar0001.png"	x="146"	y="830"	width="144"	height="192" frameX="-9" frameY="-30" frameWidth="153" frameHeight="227"/>
	<SubTexture name="FishAvatar0002.png"	x="152"	y="201"	width="141"	height="187" frameX="-12" frameY="-38" frameWidth="153" frameHeight="227"/>
	<SubTexture name="FishAvatar0003.png"	x="152"	y="389"	width="140"	height="177" frameX="-13" frameY="-46" frameWidth="153" frameHeight="227"/>
	<SubTexture name="FishAvatar0004.png"	x="291"	y="0"	width="136"	height="170" frameX="-17" frameY="-55" frameWidth="153" frameHeight="227"/>
	<SubTexture name="FishAvatar0005.png"	x="154"	y="0"	width="136"	height="163" frameX="-17" frameY="-62" frameWidth="153" frameHeight="227"/>
	<SubTexture name="FishAvatar0006.png"	x="154"	y="0"	width="136"	height="163" frameX="-17" frameY="-62" frameWidth="153" frameHeight="227"/>
	<SubTexture name="FishAvatar0007.png"	x="0"	y="0"	width="153"	height="200" frameX="-0" frameY="-27" frameWidth="153" frameHeight="227"/>
	<SubTexture name="FishAvatar0008.png"	x="0"	y="0"	width="153"	height="200" frameX="-0" frameY="-27" frameWidth="153" frameHeight="227"/>
	<SubTexture name="FishAvatar0009.png"	x="0"	y="390"	width="151"	height="216" frameX="-2" frameY="-10" frameWidth="153" frameHeight="227"/>
	<SubTexture name="FishAvatar0010.png"	x="0"	y="390"	width="151"	height="216" frameX="-2" frameY="-10" frameWidth="153" frameHeight="227"/>
	<SubTexture name="FishAvatar0011.png"	x="148"	y="607"	width="144"	height="222" frameX="-6" frameY="-0" frameWidth="153" frameHeight="227"/>
	<SubTexture name="FishAvatar0012.png"	x="148"	y="607"	width="144"	height="222" frameX="-6" frameY="-0" frameWidth="153" frameHeight="227"/>
	<SubTexture name="FishAvatar0013.png"	x="293"	y="389"	width="138"	height="223" frameX="-11" frameY="-0" frameWidth="153" frameHeight="227"/>
	<SubTexture name="FishAvatar0014.png"	x="293"	y="389"	width="138"	height="223" frameX="-11" frameY="-0" frameWidth="153" frameHeight="227"/>
	<SubTexture name="FishAvatar0015.png"	x="0"	y="805"	width="145"	height="200" frameX="-5" frameY="-3" frameWidth="153" frameHeight="227"/>
	<SubTexture name="FishAvatar0016.png"	x="0"	y="805"	width="145"	height="200" frameX="-5" frameY="-3" frameWidth="153" frameHeight="227"/>
	<SubTexture name="FishAvatar0017.png"	x="0"	y="607"	width="147"	height="197" frameX="-3" frameY="-12" frameWidth="153" frameHeight="227"/>
	<SubTexture name="FishAvatar0018.png"	x="0"	y="607"	width="147"	height="197" frameX="-3" frameY="-12" frameWidth="153" frameHeight="227"/>
	<SubTexture name="FishAvatar0019.png"	x="0"	y="201"	width="151"	height="188" frameX="-2" frameY="-31" frameWidth="153" frameHeight="227"/>
	<SubTexture name="FishAvatar0020.png"	x="0"	y="201"	width="151"	height="188" frameX="-2" frameY="-31" frameWidth="153" frameHeight="227"/>
	<SubTexture name="FishAvatar0021.png"	x="291"	y="830"	width="134"	height="162" frameX="-19" frameY="-65" frameWidth="153" frameHeight="227"/>
	<SubTexture name="FishAvatar0022.png"	x="291"	y="830"	width="134"	height="162" frameX="-19" frameY="-65" frameWidth="153" frameHeight="227"/>
	<SubTexture name="FishAvatar0023.png"	x="152"	y="201"	width="141"	height="187" frameX="-12" frameY="-38" frameWidth="153" frameHeight="227"/>
	<SubTexture name="FishAvatar0024.png"	x="152"	y="201"	width="141"	height="187" frameX="-12" frameY="-38" frameWidth="153" frameHeight="227"/>
	<SubTexture name="FishAvatar0025.png"	x="146"	y="830"	width="144"	height="192" frameX="-9" frameY="-30" frameWidth="153" frameHeight="227"/>
	<SubTexture name="FishAvatar0026.png"	x="146"	y="830"	width="144"	height="192" frameX="-9" frameY="-30" frameWidth="153" frameHeight="227"/>
</TextureAtlas>